flask_openapi3/__init__.py
flask_openapi3/http.py
flask_openapi3/markdown.py
flask_openapi3/openapi.py
flask_openapi3/utils.py
flask_openapi3/models/__init__.py
flask_openapi3/models/common.py
flask_openapi3/models/component.py
flask_openapi3/models/file.py
flask_openapi3/models/info.py
flask_openapi3/models/oauth.py
flask_openapi3/models/parameter.py
flask_openapi3/models/path.py
flask_openapi3/models/security.py
flask_openapi3/models/server.py
flask_openapi3/models/tag.py
flask_openapi3/models/validation_error.py
flask_openapi3/templates/index.html
flask_openapi3/templates/rapidoc.html
flask_openapi3/templates/redoc.html
flask_openapi3/templates/swagger.html
flask_openapi3/templates/static/css/swagger-ui.css
flask_openapi3/templates/static/images/apidoc.svg
flask_openapi3/templates/static/images/rapidoc.svg
flask_openapi3/templates/static/images/redoc.svg
flask_openapi3/templates/static/images/swagger.svg
flask_openapi3/templates/static/js/rapidoc-min.js
flask_openapi3/templates/static/js/redoc.standalone.js
flask_openapi3/templates/static/js/swagger-ui-bundle.js
flask_openapi3/templates/static/js/swagger-ui-standalone-preset.js
flask_openapi3_tarsa-1.0.2.dist-info/LICENSE.rst
flask_openapi3_tarsa-1.0.2.dist-info/METADATA
flask_openapi3_tarsa-1.0.2.dist-info/WHEEL
flask_openapi3_tarsa-1.0.2.dist-info/top_level.txt
flask_openapi3_tarsa-1.0.2.dist-info/RECORD
