Metadata-Version: 2.1
Name: flask-openapi3-tarsa
Version: 1.0.2
Summary: Generate RESTful API and OpenAPI document for your Flask project.
Home-page: https://github.com/tarcisiojr/flask-openapi3
Author: llc
Author-email: luolingchun@outlook.com
License: MIT
Platform: any
Classifier: Development Status :: 5 - Production/Stable
Classifier: Environment :: Web Environment
Classifier: Framework :: Flask
Classifier: Intended Audience :: Developers
Classifier: License :: OSI Approved :: MIT License
Classifier: Operating System :: OS Independent
Classifier: Programming Language :: Python
Classifier: Programming Language :: Python :: 3
Classifier: Programming Language :: Python :: 3.7
Classifier: Programming Language :: Python :: 3.8
Classifier: Programming Language :: Python :: 3.9
Classifier: Programming Language :: Python :: 3.10
Requires-Python: >=3.7
Requires-Dist: Flask (>=1.0)
Requires-Dist: pydantic (>=1.2)
